mcipc/__init__.py
mcipc/functions.py
mcipc/query/__init__.py
mcipc/query/client.py
mcipc/query/config.py
mcipc/query/exceptions.py
mcipc/query/queryclt.py
mcipc/query/proto/__init__.py
mcipc/query/proto/basic_stats.py
mcipc/query/proto/common.py
mcipc/query/proto/full_stats.py
mcipc/query/proto/handshake.py
mcipc/rcon/__init__.py
mcipc/rcon/client.py
mcipc/rcon/enumerations.py
mcipc/rcon/errors.py
mcipc/rcon/exceptions.py
mcipc/rcon/functions.py
mcipc/rcon/item.py
mcipc/rcon/nbt.py
mcipc/rcon/proxy.py
mcipc/rcon/types.py
mcipc/rcon/be/__init__.py
mcipc/rcon/be/client.py
mcipc/rcon/be/enumerations.py
mcipc/rcon/be/types.py
mcipc/rcon/be/commands/__init__.py
mcipc/rcon/be/commands/ability.py
mcipc/rcon/be/commands/camerashake.py
mcipc/rcon/be/commands/clear.py
mcipc/rcon/be/commands/clearspawnpoint.py
mcipc/rcon/be/commands/clone.py
mcipc/rcon/be/commands/difficulty.py
mcipc/rcon/be/commands/effect.py
mcipc/rcon/be/commands/enchant.py
mcipc/rcon/be/commands/event.py
mcipc/rcon/be/commands/fill.py
mcipc/rcon/be/commands/fog.py
mcipc/rcon/be/commands/gamemode.py
mcipc/rcon/be/commands/give.py
mcipc/rcon/be/commands/help.py
mcipc/rcon/be/commands/list.py
mcipc/rcon/be/commands/locate.py
mcipc/rcon/be/commands/mixer.py
mcipc/rcon/be/commands/mobevent.py
mcipc/rcon/be/commands/music.py
mcipc/rcon/be/commands/particle.py
mcipc/rcon/be/commands/playanimation.py
mcipc/rcon/be/commands/playsound.py
mcipc/rcon/be/commands/replaceitem.py
mcipc/rcon/be/commands/ride.py
mcipc/rcon/be/commands/save.py
mcipc/rcon/be/commands/schedule.py
mcipc/rcon/be/commands/scoreboard.py
mcipc/rcon/be/commands/setblock.py
mcipc/rcon/be/commands/setmaxplayers.py
mcipc/rcon/be/commands/setworldspawn.py
mcipc/rcon/be/commands/spawnpoint.py
mcipc/rcon/be/commands/spreadplayers.py
mcipc/rcon/be/commands/stopsound.py
mcipc/rcon/be/commands/structure.py
mcipc/rcon/be/commands/summon.py
mcipc/rcon/be/commands/teleport.py
mcipc/rcon/be/commands/testfor.py
mcipc/rcon/be/commands/testforblock.py
mcipc-2.4.2.dist-info/LICENSE.txt
mcipc-2.4.2.dist-info/METADATA
mcipc-2.4.2.dist-info/WHEEL
mcipc-2.4.2.dist-info/entry_points.txt
mcipc-2.4.2.dist-info/top_level.txt
mcipc-2.4.2.dist-info/RECORD
