Metadata-Version: 2.1
Name: mcipc
Version: 2.4.2
Summary: A Minecraft server inter-process communication library.
Home-page: https://github.com/conqp/mcipc
Author: Richard Neumann
Author-email: mail@richard-neumann.de
License: GPLv3
Keywords: minecraft python server rcon query
Platform: UNKNOWN
Requires-Python: >=3.9
License-File: LICENSE.txt
